padie_extended/__init__.py
padie_extended/cli.py
padie_extended/language_detector.py
padie_extended/core/__init__.py
padie_extended/core/constants.py
padie_extended/core/intent.py
padie_extended/core/language.py
padie_extended/core/utils.py
padie_extended/integrations/__init__.py
padie_extended/integrations/django_support/__init__.py
padie_extended/integrations/django_support/models.py
padie_extended/integrations/django_support/serializers.py
padie_extended/integrations/django_support/urls.py
padie_extended/integrations/django_support/views.py
padie_extended-0.0.8.dist-info/licenses/LICENSE
padie_extended-0.0.8.dist-info/METADATA
padie_extended-0.0.8.dist-info/WHEEL
padie_extended-0.0.8.dist-info/top_level.txt
padie_extended-0.0.8.dist-info/RECORD
