Metadata-Version: 2.4
Name: padie-extended
Version: 0.0.8
Summary: The first open-source Nigerian language text classifier on PyPI.
Author-email: Ayooluwaposi Olomo <ayooluwaposiolomo@gmail.com>
License-Expression: MIT
Project-URL: Homepage, https://github.com/posi-olomo/padie-extended
Project-URL: Issues, https://github.com/posi-olomo/padie-extended/issues
Classifier: Programming Language :: Python :: 3
Classifier: Operating System :: OS Independent
Requires-Python: >=3.9
License-File: LICENSE
Dynamic: license-file
